{
    "name": "ComunicacaoVisual",
    "alias": "comunicacao-visual",
    "description": "Modules/ComunicacaoVisual — vertical gráfica rápida e comunicação visual BR (CNAE 1813-0/01). Estado em construção (planejado piloto 2026-Q3 entre 6 saudáveis OfficeImpresso). Concorrentes: Mubisys, Zênite, Calcgraf. Diferencial: cálculo m² + PCP gráfico + apontamento + NFe-de-boleto-pago + IA conversacional. Ver memory/requisitos/ComunicacaoVisual/SPEC.md.",
    "keywords": ["comunicacao-visual", "grafica", "lona", "fachada", "plotter", "vertical", "cnae-1813"],
    "active": 1,
    "order": 0,
    "providers": [
        "Modules\\ComunicacaoVisual\\Providers\\ComunicacaoVisualServiceProvider"
    ],
    "aliases": {},
    "files": [],
    "requires": [],
    "governance": {
        "bucket": "vertical_client_facing",
        "bucket_adr": "0160",
        "bucket_config": "governance/buckets/vertical_client_facing.yaml",
        "fsm_n_a": false,
        "fsm_consumed_via": "app/Domain/Fsm/ (canon ADR 0143 — cv_ordens_producao.current_stage_id)",
        "audit_log_enabled": true,
        "audit_log_entities": ["Orcamento", "Os", "Apontamento"],
        "retention_config": "Modules/ComunicacaoVisual/Config/retention.php",
        "client_level": "backlog_hipotese",
        "wave_18_saturation": true,
        "wave_23_saturation": true,
        "wave_25_saturation": true,
        "wave_26_saturation": true,
        "scoped_score_target": 85,
        "last_governance_review": "2026-05-17",
        "rubrica_version": "v3_scoped",
        "scorecard_yaml": "memory/governance/scorecards/comunicacaovisual.yaml",
        "retention_shim": "config/retention.comunicacaovisual.php",
        "pii_lgpd_doc": "memory/requisitos/ComunicacaoVisual/PII-LGPD.md"
    }
}
